sandsldahelper/ModelBuild.py
sandsldahelper/ModelOutput.py
sandsldahelper/ModelTest.py
sandsldahelper/TextPrep.py
sandsldahelper/__init__.py
sandsldahelper-0.1.6.dist-info/LICENSE
sandsldahelper-0.1.6.dist-info/WHEEL
sandsldahelper-0.1.6.dist-info/METADATA
sandsldahelper-0.1.6.dist-info/RECORD
